setup.py
pledge/__init__.py
pledge.egg-info/PKG-INFO
pledge.egg-info/SOURCES.txt
pledge.egg-info/dependency_links.txt
pledge.egg-info/not-zip-safe
pledge.egg-info/top_level.txt