Metadata-Version: 1.0
Name: pledge
Version: 1.0
Summary:  Runs all of the preconditions. 
Home-page: https://github.com/jhorman/pledge_py
Author: Jason Horman
Author-email: jhorman@gmail.com
License: BSD
Keywords: dbc contract lambda testing
Platform: UNKNOWN
